MANIFEST.in
README.md
setup.cfg
setup.py
statemodify/__init__.py
statemodify/batch.py
statemodify/ddm.py
statemodify/ddr.py
statemodify/eva.py
statemodify/hmm.py
statemodify/modify.py
statemodify/res.py
statemodify/sampler.py
statemodify/utils.py
statemodify/xbm_iwr.py
statemodify/xdd.py
statemodify/xre.py
statemodify.egg-info/PKG-INFO
statemodify.egg-info/SOURCES.txt
statemodify.egg-info/dependency_links.txt
statemodify.egg-info/requires.txt
statemodify.egg-info/top_level.txt
statemodify/data/EightBit-Atari-Regular.ttf
statemodify/data/LHsamples_CO.txt
statemodify/data/README.md
statemodify/data/all_basins.csv
statemodify/data/background.png
statemodify/data/basin_specification.yml
statemodify/data/cm2015B.ddm
statemodify/data/cm2015B.ddr
statemodify/data/cm2015B.eva
statemodify/data/cm2015B.iwr
statemodify/data/cm2015B.res
statemodify/data/cm2015B.rsp
statemodify/data/cm2015B.xbm
statemodify/data/cm2015B.xre
statemodify/data/corrina.midi
statemodify/data/covariance_matrix_dry.txt
statemodify/data/covariance_matrix_wet.txt
statemodify/data/ddm_data_specification.yml
statemodify/data/ddr_data_specification.yml
statemodify/data/dry_state_means.txt
statemodify/data/eva_data_specification.yml
statemodify/data/gm2015B.ddm
statemodify/data/gm2015B.ddr
statemodify/data/gm2015B.eva
statemodify/data/gm2015B.iwr
statemodify/data/gm2015B.res
statemodify/data/gm2015B.rsp
statemodify/data/gm2015B.xbm
statemodify/data/gm2015B.xre
statemodify/data/iwr_data_specification.yml
statemodify/data/parameter_definitions.yml
statemodify/data/res_data_specification.yml
statemodify/data/sj2015B.ddm
statemodify/data/sj2015B.ddr
statemodify/data/sj2015B.eva
statemodify/data/sj2015B.iwr
statemodify/data/sj2015B.res
statemodify/data/sj2015B.rsp
statemodify/data/sj2015B.xbm
statemodify/data/sj2015B.xre
statemodify/data/test.parquet
statemodify/data/test.xdd
statemodify/data/transition_matrix.txt
statemodify/data/uncertain_params_original.txt
statemodify/data/wet_state_means.txt
statemodify/data/wm2015B.ddm
statemodify/data/wm2015B.ddr
statemodify/data/wm2015B.eva
statemodify/data/wm2015B.iwr
statemodify/data/wm2015B.res
statemodify/data/wm2015B.rsp
