Metadata-Version: 2.1
Name: statemodify
Version: 0.1.4
Summary: A package to modify StateMod's input and output files for exploratory modeling
Home-page: https://github.com/IMMM-SFA/statemodify
Author: Rohini S. Gupta, Chris R. Vernon
Author-email: 
License: BSD-2-Clause
Platform: UNKNOWN
Requires-Python: >=3.8
